gdwrapper/__init__.py
gdwrapper-0.0.3.dist-info/LICENSE
gdwrapper-0.0.3.dist-info/METADATA
gdwrapper-0.0.3.dist-info/WHEEL
gdwrapper-0.0.3.dist-info/top_level.txt
gdwrapper-0.0.3.dist-info/RECORD
